packageinit/__init__.py
packageinit/packageinit.py
packageinit-1.0.dist-info/LICENSE
packageinit-1.0.dist-info/METADATA
packageinit-1.0.dist-info/WHEEL
packageinit-1.0.dist-info/entry_points.txt
packageinit-1.0.dist-info/top_level.txt
packageinit-1.0.dist-info/RECORD
