Metadata-Version: 2.1
Name: packageinit
Version: 1.0
Home-page: https://github.com/yannikkellerde/packageinit
Author: Yannik Keller
Author-email: yannik@kelnet.de
License: MIT
Classifier: License :: OSI Approved :: MIT License
Classifier: Programming Language :: Python
Classifier: Programming Language :: Python :: 3
License-File: LICENSE
